<?xml version="1.0" ?>
<document id="8dedaee19e09c9fd5a849dda12a4521ea675b1a4">
  <chunk id="8dedaee19e09c9fd5a849dda12a4521ea675b1a4.c0" text="Press Accidental Chlorine Gas Intoxication: Evaluation of 39 Patients">
    <entity charOffset="26-29" id="8dedaee19e09c9fd5a849dda12a4521ea675b1a4.c0.e0" ontology_id="GO_0034005" text="Gas" type="gene_function"/>
  </chunk>
  <chunk id="8dedaee19e09c9fd5a849dda12a4521ea675b1a4.c1" text="Chlorine is a known pulmonary irritant gas that may cause acute damage in the respiratory system. In this paper, the socio-demographic and clinical characteristics of 39 accidentally exposed patients to chlorine gas are reported and different emergency treatment modalities are also discussed.">
    <entity charOffset="39-42" id="8dedaee19e09c9fd5a849dda12a4521ea675b1a4.c1.e0" ontology_id="GO_0034005" text="gas" type="gene_function"/>
    <entity charOffset="58-63" id="8dedaee19e09c9fd5a849dda12a4521ea675b1a4.c1.e1" ontology_id="HP_0011009" text="acute" type="phenotype"/>
    <entity charOffset="212-215" id="8dedaee19e09c9fd5a849dda12a4521ea675b1a4.c1.e2" ontology_id="GO_0034005" text="gas" type="gene_function"/>
    <pair e1="8dedaee19e09c9fd5a849dda12a4521ea675b1a4.c1.e0" e2="8dedaee19e09c9fd5a849dda12a4521ea675b1a4.c1.e1" id="8dedaee19e09c9fd5a849dda12a4521ea675b1a4.c1.p0" relation="true"/>
    <pair e1="8dedaee19e09c9fd5a849dda12a4521ea675b1a4.c1.e1" e2="8dedaee19e09c9fd5a849dda12a4521ea675b1a4.c1.e2" id="8dedaee19e09c9fd5a849dda12a4521ea675b1a4.c1.p1" relation="true"/>
  </chunk>
  <chunk id="8dedaee19e09c9fd5a849dda12a4521ea675b1a4.c2" text="Methods: Two emergency departments' applications were retrospectively analyzed for evaluation of accidental chlorine gas exposure for year 2007. Patients were classified into 3 groups according to severity of clinical and laboratory findings based on the literature and duration of land of stay in the emergency department. The first group was slightly exposed (discharged within 6 hours), second group moderately exposed (treated and observed for 24 hours), and third group was severely exposed (hospitalized). Most of the patients were initially treated with a combination of humidified oxygen, corticosteroids, and bronchodilators.">
    <entity charOffset="117-120" id="8dedaee19e09c9fd5a849dda12a4521ea675b1a4.c2.e0" ontology_id="GO_0034005" text="gas" type="gene_function"/>
    <entity charOffset="197-205" id="8dedaee19e09c9fd5a849dda12a4521ea675b1a4.c2.e1" ontology_id="HP_0012824" text="severity" type="phenotype"/>
    <pair e1="8dedaee19e09c9fd5a849dda12a4521ea675b1a4.c2.e0" e2="8dedaee19e09c9fd5a849dda12a4521ea675b1a4.c2.e1" id="8dedaee19e09c9fd5a849dda12a4521ea675b1a4.c2.p0" relation="true"/>
  </chunk>
  <chunk id="8dedaee19e09c9fd5a849dda12a4521ea675b1a4.c3" text="The average age was 17.03 ± 16.01 years (95% CI). Seven (17.9%) of them were female and 29 (74.4%) were children. Twenty-four patients (61.5%) were included in the first, nine (23.1%) were in second and six (15.4%) were in the third group. The presenting symptoms were cough, nausea, and vomiting and conjunctiva hyperemia for the first group, first group's symptoms plus dyspnea for the second group. Second group's symptoms plus palpitation, weakness and chest tightness were for the third group. Cough and dyspnea were seen in 64.1% and 30.8% of the patients respectively. No patients died.">
    <entity charOffset="269-274" id="8dedaee19e09c9fd5a849dda12a4521ea675b1a4.c3.e0" ontology_id="HP_0012735" text="cough" type="phenotype"/>
    <entity charOffset="288-296" id="8dedaee19e09c9fd5a849dda12a4521ea675b1a4.c3.e1" ontology_id="HP_0002013" text="vomiting" type="phenotype"/>
    <entity charOffset="372-379" id="8dedaee19e09c9fd5a849dda12a4521ea675b1a4.c3.e2" ontology_id="HP_0002094" text="dyspnea" type="phenotype"/>
    <entity charOffset="457-472" id="8dedaee19e09c9fd5a849dda12a4521ea675b1a4.c3.e3" ontology_id="HP_0031352" text="chest tightness" type="phenotype"/>
    <entity charOffset="499-504" id="8dedaee19e09c9fd5a849dda12a4521ea675b1a4.c3.e4" ontology_id="HP_0012735" text="Cough" type="phenotype"/>
    <entity charOffset="509-516" id="8dedaee19e09c9fd5a849dda12a4521ea675b1a4.c3.e5" ontology_id="HP_0002094" text="dyspnea" type="phenotype"/>
  </chunk>
  <chunk id="8dedaee19e09c9fd5a849dda12a4521ea675b1a4.c4" text="The authors recommend that non symptomatic or slightly exposed patients do not need any specific treatment or symptomatic treatment is sufficient."/>
</document>
